[
  {
    "text": "porn",
    "category": "explicit"
  },
  {
    "text": "fuck",
    "category": "explicit"
  },
  {
    "text": "ass",
    "category": "explicit"
  },
  {
    "text": "sex",
    "category": "explicit"
  },
  {
    "text": "cum",
    "category": "explicit"
  },
  {
    "text": "mature",
    "category": "explicit"
  },
  {
    "text": "busty",
    "category": "explicit"
  },
  {
    "text": "fucked",
    "category": "explicit"
  },
  {
    "text": "cock",
    "category": "explicit"
  },
  {
    "text": "milf",
    "category": "explicit"
  },
  {
    "text": "amateur",
    "category": "explicit"
  },
  {
    "text": "lesbian",
    "category": "explicit"
  },
  {
    "text": "anal",
    "category": "explicit"
  },
  {
    "text": "tit",
    "category": "explicit"
  },
  {
    "text": "pussy",
    "category": "explicit"
  },
  {
    "text": "xhamster",
    "category": "explicit"
  }
]